.gitignore
LICENSE
README.md
setup.cfg
setup.py
.idea/encodings.xml
.idea/expremigen.iml
.idea/misc.xml
.idea/modules.xml
.idea/vcs.xml
.idea/dictionaries/shimpe.xml
examples/bwv784_2voice_invention_13.py
examples/dualphrase.py
examples/example_drumpattern.py
examples/example_nanonotation.py
examples/example_readme.py
examples/mispelchords.py
examples/mispelpitchbend.py
examples/pitchbendanimation.py
examples/rubato.py
examples/singlephrase.py
examples/tuplets.py
examples/twovoicewithchords.py
examples/output/bwv784_2voice_invention_13.mid
examples/output/dualphrase.mid
examples/output/example_drumpattern.mid
examples/output/example_nanonotation.mid
examples/output/example_readme.mid
examples/output/mispelchords.mid
examples/output/mispelpitchbend.mid
examples/output/pitchbendanimation.mid
examples/output/rubato.mid
examples/output/singlephrase.mid
examples/output/tuplets.mid
examples/output/twovoicewithchords.mid
expremigen/__init__.py
expremigen.egg-info/PKG-INFO
expremigen.egg-info/SOURCES.txt
expremigen.egg-info/dependency_links.txt
expremigen.egg-info/requires.txt
expremigen.egg-info/top_level.txt
expremigen/io/__init__.py
expremigen/io/constants.py
expremigen/io/midicontrolchanges.py
expremigen/io/pat2midi.py
expremigen/io/phrase.py
expremigen/mispel/__init__.py
expremigen/mispel/exception.py
expremigen/mispel/mispel.py
expremigen/musicalmappings/__init__.py
expremigen/musicalmappings/constants.py
expremigen/musicalmappings/durations.py
expremigen/musicalmappings/dynamics.py
expremigen/musicalmappings/nanonotation.py
expremigen/musicalmappings/note2midi.py
expremigen/musicalmappings/playeddurations.py
expremigen/musicalmappings/tempo.py
expremigen/patterns/__init__.py
expremigen/patterns/padd.py
expremigen/patterns/pattern.py
expremigen/patterns/pbinop.py
expremigen/patterns/pchord.py
expremigen/patterns/pconst.py
expremigen/patterns/pexprand.py
expremigen/patterns/pgeom.py
expremigen/patterns/prand.py
expremigen/patterns/pseq.py
expremigen/patterns/pseries.py
expremigen/patterns/pshuf.py
expremigen/patterns/ptween.py
expremigen/patterns/pwhite.py
expremigen/patterns/utils.py
tests/__init__.py
tests/testgeom.py
